sldc/__init__.py
sldc/builder.py
sldc/chaining.py
sldc/classifier.py
sldc/dispatcher.py
sldc/errors.py
sldc/image.py
sldc/information.py
sldc/locator.py
sldc/logging.py
sldc/merger.py
sldc/segmenter.py
sldc/timing.py
sldc/util.py
sldc/workflow.py
sldc-1.4.2.dist-info/LICENSE.txt
sldc-1.4.2.dist-info/METADATA
sldc-1.4.2.dist-info/WHEEL
sldc-1.4.2.dist-info/top_level.txt
sldc-1.4.2.dist-info/RECORD
