Metadata-Version: 2.1
Name: sldc
Version: 1.4.2
Summary: SLDC, a generic framework for object detection and classification in large images.
Home-page: https://github.com/waliens/sldc
Author: Romain Mormont
Author-email: romain.mormont@gmail.com
Classifier: Intended Audience :: Science/Research
Classifier: Intended Audience :: Developers
Classifier: License :: OSI Approved
Classifier: Programming Language :: Python
Classifier: Topic :: Software Development
Classifier: Topic :: Scientific/Engineering
Classifier: Operating System :: POSIX
Classifier: Operating System :: Unix
Classifier: Operating System :: MacOS
Classifier: Programming Language :: Python :: 3
Classifier: Programming Language :: Python :: 3.4
Classifier: Programming Language :: Python :: 3.5
Classifier: Programming Language :: Python :: 3.6
Classifier: Programming Language :: Python :: 3.7
License-File: LICENSE.txt
Requires-Dist: rasterio
Requires-Dist: affine
Requires-Dist: pillow
Requires-Dist: numpy
Requires-Dist: joblib
Requires-Dist: shapely (>=1.8)
Requires-Dist: scikit-image
